[
  {
    "pitcher_id": 676979,
    "pitcher_name": "Garrett Crochet",
    "batter_id": 663330,
    "inning": 1,
    "inning_topbot": "Top",
    "pitch_type": "FF",
    "pitch_name": "Four-Seam Fastball",
    "start_speed": 96.3,
    "zone": 12,
    "px": 0.7800394386271041,
    "pz": 3.7956854342404336,
    "call_description": "Ball",
    "count_balls": 1,
    "count_strikes": 0,
    "outs": 0,
    "at_bat_number": 0,
    "pitch_number": 3,
    "event": "",
    "is_current": false
  },
  {
    "pitcher_id": 676979,
    "pitcher_name": "Garrett Crochet",
    "batter_id": 663330,
    "inning": 1,
    "inning_topbot": "Top",
    "pitch_type": "SI",
    "pitch_name": "Sinker",
    "start_speed": 96.2,
    "zone": 8,
    "px": 0.28462341348121833,
    "pz": 1.9699742383047183,
    "call_description": "In play, out(s)",
    "count_balls": 1,
    "count_strikes": 0,
    "outs": 0,
    "at_bat_number": 0,
    "pitch_number": 4,
    "event": "Lineout",
    "is_current": false
  },
  {
    "pitcher_id": 676979,
    "pitcher_name": "Garrett Crochet",
    "batter_id": 650402,
    "inning": 1,
    "inning_topbot": "Top",
    "pitch_type": "SI",
    "pitch_name": "Sinker",
    "start_speed": 95.3,
    "zone": 2,
    "px": 0.2192132044995416,
    "pz": 3.0083054174407957,
    "call_description": "Called Strike",
    "count_balls": 0,
    "count_strikes": 1,
    "outs": 1,
    "at_bat_number": 1,
    "pitch_number": 0,
    "event": "",
    "is_current": false
  },
  {
    "pitcher_id": 676979,
    "pitcher_name": "Garrett Crochet",
    "batter_id": 650402,
    "inning": 1,
    "inning_topbot": "Top",
    "pitch_type": "FC",
    "pitch_name": "Cutter",
    "start_speed": 88.3,
    "zone": 5,
    "px": 0.08678913416470145,
    "pz": 2.2966993786768684,
    "call_description": "Foul",
    "count_balls": 0,
    "count_strikes": 2,
    "outs": 1,
    "at_bat_number": 1,
    "pitch_number": 1,
    "event": "",
    "is_current": false
  },
  {
    "pitcher_id": 676979,
    "pitcher_name": "Garrett Crochet",
    "batter_id": 650402,
    "inning": 1,
    "inning_topbot": "Top",
    "pitch_type": "ST",
    "pitch_name": "Sweeper",
    "start_speed": 81.9,
    "zone": 13,
    "px": -0.09567643094039176,
    "pz": 0.2329664480347658,
    "call_description": "Ball",
    "count_balls": 1,
    "count_strikes": 2,
    "outs": 1,
    "at_bat_number": 1,
    "pitch_number": 2,
    "event": "",
    "is_current": false
  },
  {
    "pitcher_id": 676979,
    "pitcher_name": "Garrett Crochet",
    "batter_id": 650402,
    "inning": 1,
    "inning_topbot": "Top",
    "pitch_type": "FF",
    "pitch_name": "Four-Seam Fastball",
    "start_speed": 95.2,
    "zone": 11,
    "px": -0.7826883438308476,
    "pz": 3.51793940569223,
    "call_description": "Foul",
    "count_balls": 1,
    "count_strikes": 2,
    "outs": 1,
    "at_bat_number": 1,
    "pitch_number": 3,
    "event": "",
    "is_current": false
  },
  {
    "pitcher_id": 676979,
    "pitcher_name": "Garrett Crochet",
    "batter_id": 650402,
    "inning": 1,
    "inning_topbot": "Top",
    "pitch_type": "FC",
    "pitch_name": "Cutter",
    "start_speed": 89.4,
    "zone": 11,
    "px": -0.26018074795721563,
    "pz": 3.3576905215255906,
    "call_description": "Called Strike",
    "count_balls": 1,
    "count_strikes": 3,
    "outs": 1,
    "at_bat_number": 1,
    "pitch_number": 4,
    "event": "Strikeout",
    "is_current": false
  },
  {
    "pitcher_id": 676979,
    "pitcher_name": "Garrett Crochet",
    "batter_id": 663837,
    "inning": 1,
    "inning_topbot": "Top",
    "pitch_type": "FF",
    "pitch_name": "Four-Seam Fastball",
    "start_speed": 94.7,
    "zone": 2,
    "px": 0.02664235571303802,
    "pz": 3.027398244021794,
    "call_description": "Called Strike",
    "count_balls": 0,
    "count_strikes": 1,
    "outs": 2,
    "at_bat_number": 2,
    "pitch_number": 0,
    "event": "",
    "is_current": false
  },
  {
    "pitcher_id": 676979,
    "pitcher_name": "Garrett Crochet",
    "batter_id": 663837,
    "inning": 1,
    "inning_topbot": "Top",
    "pitch_type": "FF",
    "pitch_name": "Four-Seam Fastball",
    "start_speed": 96.7,
    "zone": 12,
    "px": 0.5276410603916559,
    "pz": 3.5597648506010695,
    "call_description": "Foul",
    "count_balls": 0,
    "count_strikes": 2,
    "outs": 2,
    "at_bat_number": 2,
    "pitch_number": 1,
    "event": "",
    "is_current": false
  },
  {
    "pitcher_id": 676979,
    "pitcher_name": "Garrett Crochet",
    "batter_id": 663837,
    "inning": 1,
    "inning_topbot": "Top",
    "pitch_type": "ST",
    "pitch_name": "Sweeper",
    "start_speed": 83.6,
    "zone": 4,
    "px": -0.23246333947681666,
    "pz": 2.2594041201246085,
    "call_description": "Foul",
    "count_balls": 0,
    "count_strikes": 2,
    "outs": 2,
    "at_bat_number": 2,
    "pitch_number": 2,
    "event": "",
    "is_current": false
  },
  {
    "pitcher_id": 676979,
    "pitcher_name": "Garrett Crochet",
    "batter_id": 663837,
    "inning": 1,
    "inning_topbot": "Top",
    "pitch_type": "ST",
    "pitch_name": "Sweeper",
    "start_speed": 81.3,
    "zone": 12,
    "px": 1.3496467455598318,
    "pz": 2.677746540479442,
    "call_description": "Ball",
    "count_balls": 1,
    "count_strikes": 2,
    "outs": 2,
    "at_bat_number": 2,
    "pitch_number": 3,
    "event": "",
    "is_current": false
  },
  {
    "pitcher_id": 676979,
    "pitcher_name": "Garrett Crochet",
    "batter_id": 663837,
    "inning": 1,
    "inning_topbot": "Top",
    "pitch_type": "FC",
    "pitch_name": "Cutter",
    "start_speed": 87.3,
    "zone": 4,
    "px": -0.3337459318537788,
    "pz": 2.3292420539890264,
    "call_description": "Foul",
    "count_balls": 1,
    "count_strikes": 2,
    "outs": 2,
    "at_bat_number": 2,
    "pitch_number": 4,
    "event": "",
    "is_current": false
  },
  {
    "pitcher_id": 676979,
    "pitcher_name": "Garrett Crochet",
    "batter_id": 663837,
    "inning": 1,
    "inning_topbot": "Top",
    "pitch_type": "FF",
    "pitch_name": "Four-Seam Fastball",
    "start_speed": 96.6,
    "zone": 8,
    "px": 0.1953416542586819,
    "pz": 2.144156899479112,
    "call_description": "Foul",
    "count_balls": 1,
    "count_strikes": 2,
    "outs": 2,
    "at_bat_number": 2,
    "pitch_number": 5,
    "event": "",
    "is_current": false
  },
  {
    "pitcher_id": 676979,
    "pitcher_name": "Garrett Crochet",
    "batter_id": 663837,
    "inning": 1,
    "inning_topbot": "Top",
    "pitch_type": "ST",
    "pitch_name": "Sweeper",
    "start_speed": 80.0,
    "zone": 3,
    "px": 0.4353150768637601,
    "pz": 3.057223043153832,
    "call_description": "In play, no out",
    "count_balls": 1,
    "count_strikes": 2,
    "outs": 2,
    "at_bat_number": 2,
    "pitch_number": 6,
    "event": "Double",
    "is_current": false
  },
  {
    "pitcher_id": 676979,
    "pitcher_name": "Garrett Crochet",
    "batter_id": 693307,
    "inning": 1,
    "inning_topbot": "Top",
    "pitch_type": "FF",
    "pitch_name": "Four-Seam Fastball",
    "start_speed": 95.4,
    "zone": 12,
    "px": 0.15239479786355578,
    "pz": 3.542905404486329,
    "call_description": "Called Strike",
    "count_balls": 0,
    "count_strikes": 1,
    "outs": 2,
    "at_bat_number": 3,
    "pitch_number": 0,
    "event": "",
    "is_current": false
  },
  {
    "pitcher_id": 676979,
    "pitcher_name": "Garrett Crochet",
    "batter_id": 693307,
    "inning": 1,
    "inning_topbot": "Top",
    "pitch_type": "FF",
    "pitch_name": "Four-Seam Fastball",
    "start_speed": 95.7,
    "zone": 12,
    "px": 0.7806376314854288,
    "pz": 3.4486582532435537,
    "call_description": "Ball",
    "count_balls": 1,
    "count_strikes": 1,
    "outs": 2,
    "at_bat_number": 3,
    "pitch_number": 2,
    "event": "",
    "is_current": false
  },
  {
    "pitcher_id": 676979,
    "pitcher_name": "Garrett Crochet",
    "batter_id": 693307,
    "inning": 1,
    "inning_topbot": "Top",
    "pitch_type": "FF",
    "pitch_name": "Four-Seam Fastball",
    "start_speed": 95.1,
    "zone": 12,
    "px": 1.2080388907911965,
    "pz": 2.867264308520676,
    "call_description": "Ball",
    "count_balls": 2,
    "count_strikes": 1,
    "outs": 2,
    "at_bat_number": 3,
    "pitch_number": 3,
    "event": "",
    "is_current": false
  },
  {
    "pitcher_id": 676979,
    "pitcher_name": "Garrett Crochet",
    "batter_id": 693307,
    "inning": 1,
    "inning_topbot": "Top",
    "pitch_type": "FC",
    "pitch_name": "Cutter",
    "start_speed": 89.9,
    "zone": 4,
    "px": -0.3587260841804877,
    "pz": 2.552595800803464,
    "call_description": "Foul",
    "count_balls": 2,
    "count_strikes": 2,
    "outs": 2,
    "at_bat_number": 3,
    "pitch_number": 4,
    "event": "",
    "is_current": false
  },
  {
    "pitcher_id": 676979,
    "pitcher_name": "Garrett Crochet",
    "batter_id": 693307,
    "inning": 1,
    "inning_topbot": "Top",
    "pitch_type": "FF",
    "pitch_name": "Four-Seam Fastball",
    "start_speed": 96.5,
    "zone": 11,
    "px": -0.7992901077122072,
    "pz": 3.182109333059061,
    "call_description": "Ball",
    "count_balls": 3,
    "count_strikes": 2,
    "outs": 2,
    "at_bat_number": 3,
    "pitch_number": 5,
    "event": "",
    "is_current": false
  },
  {
    "pitcher_id": 676979,
    "pitcher_name": "Garrett Crochet",
    "batter_id": 693307,
    "inning": 1,
    "inning_topbot": "Top",
    "pitch_type": "SI",
    "pitch_name": "Sinker",
    "start_speed": 94.7,
    "zone": 14,
    "px": 0.9659255096642602,
    "pz": 2.0417683910136057,
    "call_description": "Foul",
    "count_balls": 3,
    "count_strikes": 2,
    "outs": 2,
    "at_bat_number": 3,
    "pitch_number": 6,
    "event": "",
    "is_current": false
  },
  {
    "pitcher_id": 676979,
    "pitcher_name": "Garrett Crochet",
    "batter_id": 693307,
    "inning": 1,
    "inning_topbot": "Top",
    "pitch_type": "FC",
    "pitch_name": "Cutter",
    "start_speed": 90.2,
    "zone": 5,
    "px": 0.011607318000097202,
    "pz": 2.306797388886871,
    "call_description": "In play, run(s)",
    "count_balls": 3,
    "count_strikes": 2,
    "outs": 2,
    "at_bat_number": 3,
    "pitch_number": 7,
    "event": "Double",
    "is_current": false
  },
  {
    "pitcher_id": 676979,
    "pitcher_name": "Garrett Crochet",
    "batter_id": 682985,
    "inning": 1,
    "inning_topbot": "Top",
    "pitch_type": "SI",
    "pitch_name": "Sinker",
    "start_speed": 95.9,
    "zone": 12,
    "px": 1.1694027816947836,
    "pz": 4.003415081584942,
    "call_description": "Ball",
    "count_balls": 1,
    "count_strikes": 0,
    "outs": 2,
    "at_bat_number": 4,
    "pitch_number": 1,
    "event": "",
    "is_current": false
  },
  {
    "pitcher_id": 676979,
    "pitcher_name": "Garrett Crochet",
    "batter_id": 682985,
    "inning": 1,
    "inning_topbot": "Top",
    "pitch_type": "SI",
    "pitch_name": "Sinker",
    "start_speed": 96.9,
    "zone": 6,
    "px": 0.7900126796986673,
    "pz": 2.3731047918703596,
    "call_description": "Foul",
    "count_balls": 1,
    "count_strikes": 1,
    "outs": 2,
    "at_bat_number": 4,
    "pitch_number": 2,
    "event": "",
    "is_current": false
  },
  {
    "pitcher_id": 676979,
    "pitcher_name": "Garrett Crochet",
    "batter_id": 682985,
    "inning": 1,
    "inning_topbot": "Top",
    "pitch_type": "SI",
    "pitch_name": "Sinker",
    "start_speed": 95.4,
    "zone": 12,
    "px": 0.7962928034645068,
    "pz": 3.5391285453799677,
    "call_description": "Foul",
    "count_balls": 1,
    "count_strikes": 2,
    "outs": 2,
    "at_bat_number": 4,
    "pitch_number": 3,
    "event": "",
    "is_current": false
  },
  {
    "pitcher_id": 676979,
    "pitcher_name": "Garrett Crochet",
    "batter_id": 682985,
    "inning": 1,
    "inning_topbot": "Top",
    "pitch_type": "FF",
    "pitch_name": "Four-Seam Fastball",
    "start_speed": 96.9,
    "zone": 12,
    "px": 0.12053509512183574,
    "pz": 4.318207777897777,
    "call_description": "Swinging Strike",
    "count_balls": 1,
    "count_strikes": 3,
    "outs": 2,
    "at_bat_number": 4,
    "pitch_number": 4,
    "event": "Strikeout",
    "is_current": false
  },
  {
    "pitcher_id": 664285,
    "pitcher_name": "Framber Valdez",
    "batter_id": 701350,
    "inning": 1,
    "inning_topbot": "Bot",
    "pitch_type": "SI",
    "pitch_name": "Sinker",
    "start_speed": 93.3,
    "zone": 9,
    "px": 0.6825504293712429,
    "pz": 2.077639521149729,
    "call_description": "Called Strike",
    "count_balls": 0,
    "count_strikes": 1,
    "outs": 0,
    "at_bat_number": 5,
    "pitch_number": 0,
    "event": "",
    "is_current": false
  },
  {
    "pitcher_id": 664285,
    "pitcher_name": "Framber Valdez",
    "batter_id": 701350,
    "inning": 1,
    "inning_topbot": "Bot",
    "pitch_type": "SI",
    "pitch_name": "Sinker",
    "start_speed": 94.2,
    "zone": 12,
    "px": 1.5148341896346673,
    "pz": 3.1285094986680777,
    "call_description": "Ball",
    "count_balls": 1,
    "count_strikes": 1,
    "outs": 0,
    "at_bat_number": 5,
    "pitch_number": 1,
    "event": "",
    "is_current": false
  },
  {
    "pitcher_id": 664285,
    "pitcher_name": "Framber Valdez",
    "batter_id": 701350,
    "inning": 1,
    "inning_topbot": "Bot",
    "pitch_type": "CU",
    "pitch_name": "Curveball",
    "start_speed": 76.5,
    "zone": 14,
    "px": 1.2095860497107476,
    "pz": 2.457250625119519,
    "call_description": "Ball",
    "count_balls": 2,
    "count_strikes": 1,
    "outs": 0,
    "at_bat_number": 5,
    "pitch_number": 2,
    "event": "",
    "is_current": false
  },
  {
    "pitcher_id": 664285,
    "pitcher_name": "Framber Valdez",
    "batter_id": 701350,
    "inning": 1,
    "inning_topbot": "Bot",
    "pitch_type": "SI",
    "pitch_name": "Sinker",
    "start_speed": 93.2,
    "zone": 5,
    "px": 0.12232624246544851,
    "pz": 2.3580601364813853,
    "call_description": "In play, out(s)",
    "count_balls": 2,
    "count_strikes": 1,
    "outs": 0,
    "at_bat_number": 5,
    "pitch_number": 3,
    "event": "Groundout",
    "is_current": false
  },
  {
    "pitcher_id": 664285,
    "pitcher_name": "Framber Valdez",
    "batter_id": 655316,
    "inning": 1,
    "inning_topbot": "Bot",
    "pitch_type": "SI",
    "pitch_name": "Sinker",
    "start_speed": 93.7,
    "zone": 5,
    "px": -0.05245124167956745,
    "pz": 2.620260811629804,
    "call_description": "Called Strike",
    "count_balls": 0,
    "count_strikes": 1,
    "outs": 1,
    "at_bat_number": 6,
    "pitch_number": 0,
    "event": "",
    "is_current": false
  },
  {
    "pitcher_id": 664285,
    "pitcher_name": "Framber Valdez",
    "batter_id": 655316,
    "inning": 1,
    "inning_topbot": "Bot",
    "pitch_type": "CH",
    "pitch_name": "Changeup",
    "start_speed": 88.4,
    "zone": 14,
    "px": 0.8446789604530212,
    "pz": 2.1032547436514117,
    "call_description": "Foul",
    "count_balls": 0,
    "count_strikes": 2,
    "outs": 1,
    "at_bat_number": 6,
    "pitch_number": 1,
    "event": "",
    "is_current": false
  },
  {
    "pitcher_id": 664285,
    "pitcher_name": "Framber Valdez",
    "batter_id": 655316,
    "inning": 1,
    "inning_topbot": "Bot",
    "pitch_type": "SI",
    "pitch_name": "Sinker",
    "start_speed": 94.4,
    "zone": 13,
    "px": -1.1146639899318929,
    "pz": 2.04582527197141,
    "call_description": "Ball",
    "count_balls": 1,
    "count_strikes": 2,
    "outs": 1,
    "at_bat_number": 6,
    "pitch_number": 2,
    "event": "",
    "is_current": false
  },
  {
    "pitcher_id": 664285,
    "pitcher_name": "Framber Valdez",
    "batter_id": 655316,
    "inning": 1,
    "inning_topbot": "Bot",
    "pitch_type": "CU",
    "pitch_name": "Curveball",
    "start_speed": 78.4,
    "zone": 6,
    "px": 0.6400743931804402,
    "pz": 2.3132455843553075,
    "call_description": "Foul",
    "count_balls": 1,
    "count_strikes": 2,
    "outs": 1,
    "at_bat_number": 6,
    "pitch_number": 3,
    "event": "",
    "is_current": false
  },
  {
    "pitcher_id": 664285,
    "pitcher_name": "Framber Valdez",
    "batter_id": 655316,
    "inning": 1,
    "inning_topbot": "Bot",
    "pitch_type": "CH",
    "pitch_name": "Changeup",
    "start_speed": 89.3,
    "zone": 13,
    "px": -0.5584112804025079,
    "pz": 0.39093685865641786,
    "call_description": "Ball",
    "count_balls": 2,
    "count_strikes": 2,
    "outs": 1,
    "at_bat_number": 6,
    "pitch_number": 4,
    "event": "",
    "is_current": false
  },
  {
    "pitcher_id": 664285,
    "pitcher_name": "Framber Valdez",
    "batter_id": 655316,
    "inning": 1,
    "inning_topbot": "Bot",
    "pitch_type": "SI",
    "pitch_name": "Sinker",
    "start_speed": 94.2,
    "zone": 8,
    "px": -0.10961104235325765,
    "pz": 1.9426293966909898,
    "call_description": "In play, out(s)",
    "count_balls": 2,
    "count_strikes": 2,
    "outs": 1,
    "at_bat_number": 6,
    "pitch_number": 5,
    "event": "Groundout",
    "is_current": false
  },
  {
    "pitcher_id": 664285,
    "pitcher_name": "Framber Valdez",
    "batter_id": 575929,
    "inning": 1,
    "inning_topbot": "Bot",
    "pitch_type": "SI",
    "pitch_name": "Sinker",
    "start_speed": 92.0,
    "zone": 8,
    "px": -0.2817507533933373,
    "pz": 2.109425367361304,
    "call_description": "Foul",
    "count_balls": 0,
    "count_strikes": 1,
    "outs": 2,
    "at_bat_number": 7,
    "pitch_number": 0,
    "event": "",
    "is_current": false
  },
  {
    "pitcher_id": 664285,
    "pitcher_name": "Framber Valdez",
    "batter_id": 575929,
    "inning": 1,
    "inning_topbot": "Bot",
    "pitch_type": "SI",
    "pitch_name": "Sinker",
    "start_speed": 94.4,
    "zone": 1,
    "px": -0.3412576149312138,
    "pz": 3.4051846950806746,
    "call_description": "Called Strike",
    "count_balls": 0,
    "count_strikes": 2,
    "outs": 2,
    "at_bat_number": 7,
    "pitch_number": 1,
    "event": "",
    "is_current": false
  },
  {
    "pitcher_id": 664285,
    "pitcher_name": "Framber Valdez",
    "batter_id": 575929,
    "inning": 1,
    "inning_topbot": "Bot",
    "pitch_type": "SI",
    "pitch_name": "Sinker",
    "start_speed": 94.6,
    "zone": 7,
    "px": -0.35761033584269647,
    "pz": 2.0326551466349745,
    "call_description": "In play, run(s)",
    "count_balls": 0,
    "count_strikes": 2,
    "outs": 2,
    "at_bat_number": 7,
    "pitch_number": 2,
    "event": "Home Run",
    "is_current": false
  },
  {
    "pitcher_id": 664285,
    "pitcher_name": "Framber Valdez",
    "batter_id": 596115,
    "inning": 1,
    "inning_topbot": "Bot",
    "pitch_type": "CU",
    "pitch_name": "Curveball",
    "start_speed": 76.9,
    "zone": 14,
    "px": 0.44869819821403784,
    "pz": 1.5889978492144872,
    "call_description": "Called Strike",
    "count_balls": 0,
    "count_strikes": 1,
    "outs": 2,
    "at_bat_number": 8,
    "pitch_number": 0,
    "event": "",
    "is_current": false
  },
  {
    "pitcher_id": 664285,
    "pitcher_name": "Framber Valdez",
    "batter_id": 596115,
    "inning": 1,
    "inning_topbot": "Bot",
    "pitch_type": "CH",
    "pitch_name": "Changeup",
    "start_speed": 90.0,
    "zone": 14,
    "px": 0.40379856210515414,
    "pz": 1.444237035395464,
    "call_description": "In play, no out",
    "count_balls": 0,
    "count_strikes": 1,
    "outs": 2,
    "at_bat_number": 8,
    "pitch_number": 1,
    "event": "Single",
    "is_current": false
  },
  {
    "pitcher_id": 664285,
    "pitcher_name": "Framber Valdez",
    "batter_id": 677800,
    "inning": 1,
    "inning_topbot": "Bot",
    "pitch_type": "SI",
    "pitch_name": "Sinker",
    "start_speed": 93.2,
    "zone": 8,
    "px": -0.035688007668129226,
    "pz": 1.7517724395170349,
    "call_description": "Called Strike",
    "count_balls": 0,
    "count_strikes": 1,
    "outs": 2,
    "at_bat_number": 9,
    "pitch_number": 0,
    "event": "",
    "is_current": false
  },
  {
    "pitcher_id": 664285,
    "pitcher_name": "Framber Valdez",
    "batter_id": 677800,
    "inning": 1,
    "inning_topbot": "Bot",
    "pitch_type": "SI",
    "pitch_name": "Sinker",
    "start_speed": 93.1,
    "zone": 4,
    "px": -0.6104526953379957,
    "pz": 2.3202358268908663,
    "call_description": "Called Strike",
    "count_balls": 0,
    "count_strikes": 2,
    "outs": 2,
    "at_bat_number": 9,
    "pitch_number": 2,
    "event": "",
    "is_current": false
  },
  {
    "pitcher_id": 664285,
    "pitcher_name": "Framber Valdez",
    "batter_id": 677800,
    "inning": 1,
    "inning_topbot": "Bot",
    "pitch_type": "CU",
    "pitch_name": "Curveball",
    "start_speed": 79.3,
    "zone": 13,
    "px": -0.08572820472883604,
    "pz": 0.19938580094565458,
    "call_description": "Ball In Dirt",
    "count_balls": 1,
    "count_strikes": 2,
    "outs": 2,
    "at_bat_number": 9,
    "pitch_number": 4,
    "event": "",
    "is_current": false
  },
  {
    "pitcher_id": 664285,
    "pitcher_name": "Framber Valdez",
    "batter_id": 677800,
    "inning": 1,
    "inning_topbot": "Bot",
    "pitch_type": "CU",
    "pitch_name": "Curveball",
    "start_speed": 78.6,
    "zone": 13,
    "px": -1.290515663007235,
    "pz": 0.4714605164009342,
    "call_description": "Ball In Dirt",
    "count_balls": 2,
    "count_strikes": 2,
    "outs": 2,
    "at_bat_number": 9,
    "pitch_number": 5,
    "event": "",
    "is_current": false
  },
  {
    "pitcher_id": 664285,
    "pitcher_name": "Framber Valdez",
    "batter_id": 677800,
    "inning": 1,
    "inning_topbot": "Bot",
    "pitch_type": "SI",
    "pitch_name": "Sinker",
    "start_speed": 94.4,
    "zone": 13,
    "px": -1.6756540561478326,
    "pz": 1.465840994863178,
    "call_description": "Ball",
    "count_balls": 3,
    "count_strikes": 2,
    "outs": 2,
    "at_bat_number": 9,
    "pitch_number": 6,
    "event": "",
    "is_current": false
  },
  {
    "pitcher_id": 664285,
    "pitcher_name": "Framber Valdez",
    "batter_id": 677800,
    "inning": 1,
    "inning_topbot": "Bot",
    "pitch_type": "SI",
    "pitch_name": "Sinker",
    "start_speed": 94.1,
    "zone": 5,
    "px": -0.241659305526333,
    "pz": 2.2745237266851714,
    "call_description": "Foul",
    "count_balls": 3,
    "count_strikes": 2,
    "outs": 2,
    "at_bat_number": 9,
    "pitch_number": 7,
    "event": "",
    "is_current": false
  },
  {
    "pitcher_id": 664285,
    "pitcher_name": "Framber Valdez",
    "batter_id": 677800,
    "inning": 1,
    "inning_topbot": "Bot",
    "pitch_type": "SI",
    "pitch_name": "Sinker",
    "start_speed": 94.6,
    "zone": 8,
    "px": -0.1925130739678897,
    "pz": 2.113059733793788,
    "call_description": "Foul",
    "count_balls": 3,
    "count_strikes": 2,
    "outs": 2,
    "at_bat_number": 9,
    "pitch_number": 8,
    "event": "",
    "is_current": false
  },
  {
    "pitcher_id": 664285,
    "pitcher_name": "Framber Valdez",
    "batter_id": 677800,
    "inning": 1,
    "inning_topbot": "Bot",
    "pitch_type": "CU",
    "pitch_name": "Curveball",
    "start_speed": 78.2,
    "zone": 12,
    "px": 0.9386940167958929,
    "pz": 2.8979344350066154,
    "call_description": "Ball",
    "count_balls": 4,
    "count_strikes": 2,
    "outs": 2,
    "at_bat_number": 9,
    "pitch_number": 9,
    "event": "Walk",
    "is_current": false
  },
  {
    "pitcher_id": 664285,
    "pitcher_name": "Framber Valdez",
    "batter_id": 678882,
    "inning": 1,
    "inning_topbot": "Bot",
    "pitch_type": "CU",
    "pitch_name": "Curveball",
    "start_speed": 78.5,
    "zone": 13,
    "px": -1.107115889667967,
    "pz": 1.895808533130675,
    "call_description": "Foul",
    "count_balls": 0,
    "count_strikes": 1,
    "outs": 2,
    "at_bat_number": 10,
    "pitch_number": 0,
    "event": "",
    "is_current": false
  },
  {
    "pitcher_id": 664285,
    "pitcher_name": "Framber Valdez",
    "batter_id": 678882,
    "inning": 1,
    "inning_topbot": "Bot",
    "pitch_type": "SI",
    "pitch_name": "Sinker",
    "start_speed": 94.4,
    "zone": 13,
    "px": -0.8683185702353323,
    "pz": 2.2372649271383858,
    "call_description": "Called Strike",
    "count_balls": 0,
    "count_strikes": 2,
    "outs": 2,
    "at_bat_number": 10,
    "pitch_number": 1,
    "event": "",
    "is_current": false
  },
  {
    "pitcher_id": 664285,
    "pitcher_name": "Framber Valdez",
    "batter_id": 678882,
    "inning": 1,
    "inning_topbot": "Bot",
    "pitch_type": "SI",
    "pitch_name": "Sinker",
    "start_speed": 94.7,
    "zone": 1,
    "px": -0.6267600675721833,
    "pz": 3.2472763858469857,
    "call_description": "Called Strike",
    "count_balls": 0,
    "count_strikes": 3,
    "outs": 2,
    "at_bat_number": 10,
    "pitch_number": 2,
    "event": "Strikeout",
    "is_current": false
  },
  {
    "pitcher_id": 676979,
    "pitcher_name": "Garrett Crochet",
    "batter_id": 672761,
    "inning": 2,
    "inning_topbot": "Top",
    "pitch_type": "FF",
    "pitch_name": "Four-Seam Fastball",
    "start_speed": 95.3,
    "zone": 4,
    "px": -0.6875845293099168,
    "pz": 2.408025871637571,
    "call_description": "Called Strike",
    "count_balls": 0,
    "count_strikes": 1,
    "outs": 0,
    "at_bat_number": 11,
    "pitch_number": 0,
    "event": "",
    "is_current": false
  },
  {
    "pitcher_id": 676979,
    "pitcher_name": "Garrett Crochet",
    "batter_id": 672761,
    "inning": 2,
    "inning_topbot": "Top",
    "pitch_type": "FF",
    "pitch_name": "Four-Seam Fastball",
    "start_speed": 95.1,
    "zone": 3,
    "px": 0.47506625601703195,
    "pz": 3.1598511821889175,
    "call_description": "Foul",
    "count_balls": 0,
    "count_strikes": 2,
    "outs": 0,
    "at_bat_number": 11,
    "pitch_number": 1,
    "event": "",
    "is_current": false
  },
  {
    "pitcher_id": 676979,
    "pitcher_name": "Garrett Crochet",
    "batter_id": 672761,
    "inning": 2,
    "inning_topbot": "Top",
    "pitch_type": "ST",
    "pitch_name": "Sweeper",
    "start_speed": 82.0,
    "zone": 8,
    "px": 0.24951026607174034,
    "pz": 1.9013939286889157,
    "call_description": "Called Strike",
    "count_balls": 0,
    "count_strikes": 3,
    "outs": 0,
    "at_bat_number": 11,
    "pitch_number": 3,
    "event": "Strikeout",
    "is_current": false
  },
  {
    "pitcher_id": 676979,
    "pitcher_name": "Garrett Crochet",
    "batter_id": 679529,
    "inning": 2,
    "inning_topbot": "Top",
    "pitch_type": "FC",
    "pitch_name": "Cutter",
    "start_speed": 92.3,
    "zone": 2,
    "px": 0.07084759275879363,
    "pz": 3.0849590877194246,
    "call_description": "Called Strike",
    "count_balls": 0,
    "count_strikes": 1,
    "outs": 1,
    "at_bat_number": 12,
    "pitch_number": 0,
    "event": "",
    "is_current": false
  },
  {
    "pitcher_id": 676979,
    "pitcher_name": "Garrett Crochet",
    "batter_id": 679529,
    "inning": 2,
    "inning_topbot": "Top",
    "pitch_type": "ST",
    "pitch_name": "Sweeper",
    "start_speed": 81.2,
    "zone": 12,
    "px": 1.8147929294310567,
    "pz": 3.4298961982165004,
    "call_description": "Ball",
    "count_balls": 1,
    "count_strikes": 1,
    "outs": 1,
    "at_bat_number": 12,
    "pitch_number": 2,
    "event": "",
    "is_current": false
  },
  {
    "pitcher_id": 676979,
    "pitcher_name": "Garrett Crochet",
    "batter_id": 679529,
    "inning": 2,
    "inning_topbot": "Top",
    "pitch_type": "FC",
    "pitch_name": "Cutter",
    "start_speed": 92.3,
    "zone": 8,
    "px": 0.1608793816323238,
    "pz": 1.607514797823516,
    "call_description": "Ball",
    "count_balls": 2,
    "count_strikes": 1,
    "outs": 1,
    "at_bat_number": 12,
    "pitch_number": 3,
    "event": "",
    "is_current": false
  },
  {
    "pitcher_id": 676979,
    "pitcher_name": "Garrett Crochet",
    "batter_id": 679529,
    "inning": 2,
    "inning_topbot": "Top",
    "pitch_type": "FF",
    "pitch_name": "Four-Seam Fastball",
    "start_speed": 94.6,
    "zone": 14,
    "px": 1.1014377920290601,
    "pz": 2.1541198222321443,
    "call_description": "Ball",
    "count_balls": 3,
    "count_strikes": 1,
    "outs": 1,
    "at_bat_number": 12,
    "pitch_number": 4,
    "event": "",
    "is_current": false
  },
  {
    "pitcher_id": 676979,
    "pitcher_name": "Garrett Crochet",
    "batter_id": 679529,
    "inning": 2,
    "inning_topbot": "Top",
    "pitch_type": "FC",
    "pitch_name": "Cutter",
    "start_speed": 91.9,
    "zone": 12,
    "px": 1.0571097715221303,
    "pz": 3.1361421674951964,
    "call_description": "Ball",
    "count_balls": 4,
    "count_strikes": 1,
    "outs": 1,
    "at_bat_number": 12,
    "pitch_number": 5,
    "event": "Walk",
    "is_current": false
  },
  {
    "pitcher_id": 676979,
    "pitcher_name": "Garrett Crochet",
    "batter_id": 701678,
    "inning": 2,
    "inning_topbot": "Top",
    "pitch_type": "FF",
    "pitch_name": "Four-Seam Fastball",
    "start_speed": 95.6,
    "zone": 13,
    "px": -1.136153213786354,
    "pz": 2.3674834601900923,
    "call_description": "Ball",
    "count_balls": 1,
    "count_strikes": 0,
    "outs": 1,
    "at_bat_number": 13,
    "pitch_number": 0,
    "event": "",
    "is_current": true
  }
]